routix/__init__.py
routix/constants.py
routix/dynamic_data_object.py
routix/elapsed_timer.py
routix/io.py
routix/method_context_manager.py
routix/py.typed
routix/solution_manager.py
routix/stopping_criteria.py
routix/subroutine_controller.py
routix/subroutine_flow_validator.py
routix/type_defs.py
routix/metric_time_series/__init__.py
routix/metric_time_series/metric_time_series.py
routix/metric_time_series/named_time_series_store.py
routix/report/__init__.py
routix/report/subroutine_report.py
routix/report/subroutine_report_statistics.py
routix/runner/README.md
routix/runner/__init__.py
routix/runner/multi_instance_concurrent_runner.py
routix/runner/multi_instance_runner.py
routix/runner/multi_scenario_runner.py
routix/runner/single_instance_runner.py
routix-0.0.13.dist-info/METADATA
routix-0.0.13.dist-info/WHEEL
routix-0.0.13.dist-info/RECORD
