Metadata-Version: 2.4
Name: routix
Version: 0.0.13
Summary: Define routines as structured algorithmic workflows
Project-URL: Repository, https://github.com/MSOlab/routix.git
Author-email: JuneTech <junetech0@gmail.com>
License-Expression: MIT
Requires-Python: >=3.11
